certbox/__init__.py
certbox/__main__.py
certbox/app.py
certbox/auth.py
certbox/cli.py
certbox/config.py
certbox/api/__init__.py
certbox/api/routes.py
certbox/core/__init__.py
certbox/core/certificate_manager.py
certbox-1.1.2.dist-info/licenses/LICENSE
certbox-1.1.2.dist-info/METADATA
certbox-1.1.2.dist-info/WHEEL
certbox-1.1.2.dist-info/entry_points.txt
certbox-1.1.2.dist-info/top_level.txt
certbox-1.1.2.dist-info/RECORD
