Metadata-Version: 2.4
Name: certbox
Version: 1.1.2
Summary: X.509 Certificate Management Service
Home-page: https://github.com/gisce/certbox
Author: GISCE-TI
Author-email: devel@gisce.net
Classifier: Development Status :: 4 - Beta
Classifier: Intended Audience :: Developers
Classifier: License :: OSI Approved :: MIT License
Classifier: Operating System :: OS Independent
Classifier: Programming Language :: Python :: 3
Classifier: Programming Language :: Python :: 3.8
Classifier: Programming Language :: Python :: 3.9
Classifier: Programming Language :: Python :: 3.10
Classifier: Programming Language :: Python :: 3.11
Classifier: Programming Language :: Python :: 3.12
Classifier: Topic :: Security :: Cryptography
Classifier: Topic :: Internet :: WWW/HTTP :: HTTP Servers
Requires-Python: >=3.8
License-File: LICENSE
Dynamic: author
Dynamic: author-email
Dynamic: classifier
Dynamic: description
Dynamic: description-content-type
Dynamic: home-page
Dynamic: license-file
Dynamic: requires-python
Dynamic: summary
